atomic6ghg/LICENSE
atomic6ghg/README.md
atomic6ghg/__init__.py
atomic6ghg/__main__.py
atomic6ghg/exceptions.py
atomic6ghg/pyproject.toml
atomic6ghg/factors/__init__.py
atomic6ghg/factors/business_travel_factors.py
atomic6ghg/factors/electricity_emission_factors.py
atomic6ghg/factors/fire_suppression_leak_rates_factors.py
atomic6ghg/factors/heat_content_factors.py
atomic6ghg/factors/mobile_combustion_ch4_and_n2o_emission_factors.py
atomic6ghg/factors/mobile_combustion_co2_emission_factors.py
atomic6ghg/factors/molecular_weights_factors.py
atomic6ghg/factors/product_transport_emission_factors.py
atomic6ghg/factors/refrigerants_gwp_factors.py
atomic6ghg/factors/refrigeration_and_ac_equipment_emission_factors.py
atomic6ghg/factors/stationary_combustion_emission_factors.py
atomic6ghg/factors/unit_conversions_factors.py
atomic6ghg/factors/waste_emission_factors.py
atomic6ghg/factors/source_data/business_travel_factors.json
atomic6ghg/factors/source_data/electricity_emission_factors.json
atomic6ghg/factors/source_data/fire_suppression_leak_rates_factors.json
atomic6ghg/factors/source_data/heat_content_factors.json
atomic6ghg/factors/source_data/mobile_combustion_ch4_and_n2o_emission_factors.json
atomic6ghg/factors/source_data/mobile_combustion_co2_emission_factors.json
atomic6ghg/factors/source_data/molecular_weights_factors.json
atomic6ghg/factors/source_data/product_transport_emission_factors.json
atomic6ghg/factors/source_data/refrigerants_gwp_factors.json
atomic6ghg/factors/source_data/refrigeration_and_ac_equipment_emission_factors.json
atomic6ghg/factors/source_data/stationary_combustion_emission_factors.json
atomic6ghg/factors/source_data/unit_conversions_factors.json
atomic6ghg/factors/source_data/waste_emission_factors.json
atomic6ghg/formulas/__init__.py
atomic6ghg/formulas/business_travel.py
atomic6ghg/formulas/commuting.py
atomic6ghg/formulas/electricity.py
atomic6ghg/formulas/fire_suppression.py
atomic6ghg/formulas/formula.py
atomic6ghg-1.1.1.dist-info/METADATA
atomic6ghg-1.1.1.dist-info/WHEEL
atomic6ghg-1.1.1.dist-info/licenses/LICENSE
atomic6ghg-1.1.1.dist-info/RECORD
