Metadata-Version: 2.1
Name: atomic6ghg
Version: 1.1.1
Summary: Library of formulas, conversion factors and schemas for greenhouse gas calculations
Project-URL: repository, https://github.com/Glasmor/atomic6ghg
Project-URL: homepage, https://glasmorsoftware.com
Author-email: Kevin C Kelly <kkelly@glasmor.io>, Dave McGhan <dave.mcghan@ge.com>, Macenzie Mitchell <mackenziemitchell6@gmail.com>, Danial Oh <danial.oh@ge.com>, Mark Diehr <mark.diehr@ge.com>
Maintainer-email: Kevin C Kelly <kkelly@glasmor.io>
License: BSD 3-Clause License
License-File: LICENSE
Keywords: Carbon Accounting,ClimateTech,GHG Protocol
Classifier: Development Status :: 5 - Production/Stable
Classifier: License :: OSI Approved :: BSD License
Classifier: Programming Language :: Python :: 3
Classifier: Programming Language :: Python :: 3.10
Classifier: Programming Language :: Python :: 3.11
Requires-Python: >=3.10
Provides-Extra: dev
Requires-Dist: black; extra == 'dev'
Requires-Dist: jsonschema; extra == 'dev'
Requires-Dist: mypy; extra == 'dev'
Requires-Dist: pip-tools; extra == 'dev'
Requires-Dist: pylint; extra == 'dev'
Requires-Dist: pytest; extra == 'dev'
